{"winner": 1, "player_0_champion": 80, "player_0_points": 2230, "player_0_winrate": 0.4858757062146893, "player_0_summoner_level": 461, "player_0_last_10_winrate": 0.2, "player_0_hotstreak": 0, "player_1_champion": 121, "player_1_points": 2333, "player_1_winrate": 0.4751131221719457, "player_1_summoner_level": 85, "player_1_last_10_winrate": 0.4, "player_1_hotstreak": 0, "player_2_champion": 134, "player_2_points": 2400, "player_2_winrate": 0.6029411764705882, "player_2_summoner_level": 107, "player_2_last_10_winrate": 0.7, "player_2_hotstreak": 0, "player_3_champion": 145, "player_3_points": 2493, "player_3_winrate": 0.5306748466257669, "player_3_summoner_level": 303, "player_3_last_10_winrate": 0.5, "player_3_hotstreak": 0, "player_4_champion": 16, "player_4_points": 2250, "player_4_winrate": 0.5555555555555556, "player_4_summoner_level": 659, "player_4_last_10_winrate": 0.2, "player_4_hotstreak": 0, "player_5_champion": 48, "player_5_points": 2491, "player_5_winrate": 0.5207667731629393, "player_5_summoner_level": 233, "player_5_last_10_winrate": 0.6, "player_5_hotstreak": 0, "player_6_champion": 60, "player_6_points": 2349, "player_6_winrate": 0.5, "player_6_summoner_level": 62, "player_6_last_10_winrate": 0.5, "player_6_hotstreak": 0, "player_7_champion": 91, "player_7_points": 2357, "player_7_winrate": 0.5220125786163522, "player_7_summoner_level": 272, "player_7_last_10_winrate": 0.4, "player_7_hotstreak": 0, "player_8_champion": 81, "player_8_points": 2251, "player_8_winrate": 0.4594594594594595, "player_8_summoner_level": 177, "player_8_last_10_winrate": 0.3, "player_8_hotstreak": 0, "player_9_champion": 12, "player_9_points": 2336, "player_9_winrate": 0.5098634294385432, "player_9_summoner_level": 639, "player_9_last_10_winrate": 0.5, "player_9_hotstreak": 0}