{"winner": 1, "player_0_champion": 897, "player_0_points": 3290, "player_0_winrate": 0.5336426914153132, "player_0_summoner_level": 312, "player_0_last_10_winrate": 0.5, "player_0_hotstreak": 0, "player_1_champion": 79, "player_1_points": 3322, "player_1_winrate": 0.5233918128654971, "player_1_summoner_level": 598, "player_1_last_10_winrate": 0.3, "player_1_hotstreak": 0, "player_2_champion": 166, "player_2_points": 3179, "player_2_winrate": 0.5978835978835979, "player_2_summoner_level": 89, "player_2_last_10_winrate": 0.4, "player_2_hotstreak": 0, "player_3_champion": 119, "player_3_points": 3513, "player_3_winrate": 0.5197860962566845, "player_3_summoner_level": 362, "player_3_last_10_winrate": 0.6, "player_3_hotstreak": 0, "player_4_champion": 111, "player_4_points": 3576, "player_4_winrate": 0.5490566037735849, "player_4_summoner_level": 252, "player_4_last_10_winrate": 0.3, "player_4_hotstreak": 0, "player_5_champion": 2, "player_5_points": 3823, "player_5_winrate": 0.5758293838862559, "player_5_summoner_level": 159, "player_5_last_10_winrate": 0.5, "player_5_hotstreak": 0, "player_6_champion": 68, "player_6_points": 3468, "player_6_winrate": 0.5212962962962963, "player_6_summoner_level": 234, "player_6_last_10_winrate": 0.7, "player_6_hotstreak": 0, "player_7_champion": 234, "player_7_points": 3575, "player_7_winrate": 0.5226244343891403, "player_7_summoner_level": 892, "player_7_last_10_winrate": 0.9, "player_7_hotstreak": 1, "player_8_champion": 498, "player_8_points": 3157, "player_8_winrate": 0.5294117647058824, "player_8_summoner_level": 1015, "player_8_last_10_winrate": 0.5, "player_8_hotstreak": 0, "player_9_champion": 902, "player_9_points": 3001, "player_9_winrate": 0.5085551330798479, "player_9_summoner_level": 1119, "player_9_last_10_winrate": 0.3, "player_9_hotstreak": 0}