{"winner": 1, "player_0_champion": 79, "player_0_points": 3354, "player_0_winrate": 0.5223665223665224, "player_0_summoner_level": 873, "player_0_last_10_winrate": 0.6, "player_0_hotstreak": 1, "player_1_champion": 200, "player_1_points": 3446, "player_1_winrate": 0.533026113671275, "player_1_summoner_level": 589, "player_1_last_10_winrate": 0.4, "player_1_hotstreak": 0, "player_2_champion": 166, "player_2_points": 3609, "player_2_winrate": 0.529192546583851, "player_2_summoner_level": 454, "player_2_last_10_winrate": 0.7, "player_2_hotstreak": 0, "player_3_champion": 30, "player_3_points": 3334, "player_3_winrate": 0.5444126074498568, "player_3_summoner_level": 319, "player_3_last_10_winrate": 0.4, "player_3_hotstreak": 0, "player_4_champion": 235, "player_4_points": 3198, "player_4_winrate": 0.5151515151515151, "player_4_summoner_level": 876, "player_4_last_10_winrate": 0.2, "player_4_hotstreak": 0, "player_5_champion": 897, "player_5_points": 3409, "player_5_winrate": 0.5237154150197628, "player_5_summoner_level": 553, "player_5_last_10_winrate": 0.8, "player_5_hotstreak": 0, "player_6_champion": 245, "player_6_points": 3422, "player_6_winrate": 0.6108374384236454, "player_6_summoner_level": 215, "player_6_last_10_winrate": 0.7, "player_6_hotstreak": 0, "player_7_champion": 104, "player_7_points": 3596, "player_7_winrate": 0.5272496831432193, "player_7_summoner_level": 496, "player_7_last_10_winrate": 0.7, "player_7_hotstreak": 1, "player_8_champion": 523, "player_8_points": 3415, "player_8_winrate": 0.5220680958385876, "player_8_summoner_level": 1051, "player_8_last_10_winrate": 0.7, "player_8_hotstreak": 0, "player_9_champion": 412, "player_9_points": 3328, "player_9_winrate": 0.5268630849220104, "player_9_summoner_level": 193, "player_9_last_10_winrate": 0.3, "player_9_hotstreak": 0}