{"winner": 1, "player_0_champion": 516, "player_0_points": 1303, "player_0_winrate": 0.4519230769230769, "player_0_summoner_level": 625, "player_0_last_10_winrate": 0.4, "player_0_hotstreak": 0, "player_1_champion": 11, "player_1_points": 1359, "player_1_winrate": 0.5181347150259067, "player_1_summoner_level": 46, "player_1_last_10_winrate": 0.5, "player_1_hotstreak": 0, "player_2_champion": 268, "player_2_points": 1300, "player_2_winrate": 0.5283842794759825, "player_2_summoner_level": 168, "player_2_last_10_winrate": 0.5, "player_2_hotstreak": 0, "player_3_champion": 29, "player_3_points": 1349, "player_3_winrate": 0.4756554307116105, "player_3_summoner_level": 473, "player_3_last_10_winrate": 0.4, "player_3_hotstreak": 0, "player_4_champion": 50, "player_4_points": 1235, "player_4_winrate": 0.4883720930232558, "player_4_summoner_level": 265, "player_4_last_10_winrate": 0.5, "player_4_hotstreak": 0, "player_5_champion": 14, "player_5_points": 1241, "player_5_winrate": 0.4642857142857143, "player_5_summoner_level": 42, "player_5_last_10_winrate": 0.4, "player_5_hotstreak": 0, "player_6_champion": 19, "player_6_points": -1, "player_6_winrate": -1, "player_6_summoner_level": 30, "player_6_last_10_winrate": 0.375, "player_6_hotstreak": false, "player_7_champion": 131, "player_7_points": 1300, "player_7_winrate": 0.5149700598802395, "player_7_summoner_level": 296, "player_7_last_10_winrate": 0.3, "player_7_hotstreak": 0, "player_8_champion": 96, "player_8_points": 1200, "player_8_winrate": 0.45054945054945056, "player_8_summoner_level": 42, "player_8_last_10_winrate": 0.4, "player_8_hotstreak": 0, "player_9_champion": 117, "player_9_points": 1160, "player_9_winrate": 0.42857142857142855, "player_9_summoner_level": 288, "player_9_last_10_winrate": 0.3, "player_9_hotstreak": 0}