{"winner": 2, "player_0_champion": 516, "player_0_points": 1124, "player_0_winrate": 0.5032851511169514, "player_0_summoner_level": 292, "player_0_last_10_winrate": 0.5, "player_0_hotstreak": 0, "player_1_champion": 141, "player_1_points": 1054, "player_1_winrate": 0.48148148148148145, "player_1_summoner_level": 451, "player_1_last_10_winrate": 0.3, "player_1_hotstreak": 0, "player_2_champion": 238, "player_2_points": 1028, "player_2_winrate": 0.475, "player_2_summoner_level": 397, "player_2_last_10_winrate": 0.4, "player_2_hotstreak": 0, "player_3_champion": 119, "player_3_points": 1145, "player_3_winrate": 0.539622641509434, "player_3_summoner_level": 339, "player_3_last_10_winrate": 0.6, "player_3_hotstreak": 1, "player_4_champion": 902, "player_4_points": 1026, "player_4_winrate": 0.5017543859649123, "player_4_summoner_level": 454, "player_4_last_10_winrate": 0.4, "player_4_hotstreak": 0, "player_5_champion": 150, "player_5_points": 1126, "player_5_winrate": 0.48872180451127817, "player_5_summoner_level": 191, "player_5_last_10_winrate": 0.6, "player_5_hotstreak": 0, "player_6_champion": 245, "player_6_points": -1, "player_6_winrate": -1, "player_6_summoner_level": 30, "player_6_last_10_winrate": 0.25, "player_6_hotstreak": false, "player_7_champion": 157, "player_7_points": 1292, "player_7_winrate": 0.5133689839572193, "player_7_summoner_level": 174, "player_7_last_10_winrate": 0.7, "player_7_hotstreak": 1, "player_8_champion": 221, "player_8_points": 800, "player_8_winrate": 0.5384615384615384, "player_8_summoner_level": 32, "player_8_last_10_winrate": 0.5, "player_8_hotstreak": 0, "player_9_champion": 147, "player_9_points": 1238, "player_9_winrate": 0.5203252032520326, "player_9_summoner_level": 311, "player_9_last_10_winrate": 0.6, "player_9_hotstreak": 0}