{"winner": 1, "player_0_champion": 420, "player_0_points": 3326, "player_0_winrate": 0.5578635014836796, "player_0_summoner_level": 340, "player_0_last_10_winrate": 0.6, "player_0_hotstreak": 0, "player_1_champion": 79, "player_1_points": 3076, "player_1_winrate": 0.514585764294049, "player_1_summoner_level": 388, "player_1_last_10_winrate": 0.6, "player_1_hotstreak": 0, "player_2_champion": 238, "player_2_points": 3501, "player_2_winrate": 0.5206073752711496, "player_2_summoner_level": 989, "player_2_last_10_winrate": 0.5, "player_2_hotstreak": 1, "player_3_champion": 236, "player_3_points": 3308, "player_3_winrate": 0.5484848484848485, "player_3_summoner_level": 676, "player_3_last_10_winrate": 0.7, "player_3_hotstreak": 0, "player_4_champion": 267, "player_4_points": 3338, "player_4_winrate": 0.5605381165919282, "player_4_summoner_level": 351, "player_4_last_10_winrate": 0.5, "player_4_hotstreak": 0, "player_5_champion": 516, "player_5_points": 2967, "player_5_winrate": 0.5104972375690607, "player_5_summoner_level": 316, "player_5_last_10_winrate": 0.6, "player_5_hotstreak": 0, "player_6_champion": 141, "player_6_points": 2855, "player_6_winrate": 0.5193482688391039, "player_6_summoner_level": 498, "player_6_last_10_winrate": 0.4, "player_6_hotstreak": 0, "player_7_champion": 142, "player_7_points": 3138, "player_7_winrate": 0.5095057034220533, "player_7_summoner_level": 370, "player_7_last_10_winrate": 0.3, "player_7_hotstreak": 0, "player_8_champion": 222, "player_8_points": 3145, "player_8_winrate": 0.5376532399299475, "player_8_summoner_level": 72, "player_8_last_10_winrate": 0.4, "player_8_hotstreak": 0, "player_9_champion": 902, "player_9_points": 3158, "player_9_winrate": 0.5304740406320542, "player_9_summoner_level": 770, "player_9_last_10_winrate": 0.4, "player_9_hotstreak": 0}