{"winner": 1, "player_0_champion": 2, "player_0_points": 1665, "player_0_winrate": 0.4963235294117647, "player_0_summoner_level": 449, "player_0_last_10_winrate": 0.6, "player_0_hotstreak": 0, "player_1_champion": 121, "player_1_points": 1600, "player_1_winrate": 0.5697674418604651, "player_1_summoner_level": 205, "player_1_last_10_winrate": 0.1, "player_1_hotstreak": 0, "player_2_champion": 55, "player_2_points": 1600, "player_2_winrate": 0.509375, "player_2_summoner_level": 350, "player_2_last_10_winrate": 0.1, "player_2_hotstreak": 0, "player_3_champion": 222, "player_3_points": 1703, "player_3_winrate": 0.4676258992805755, "player_3_summoner_level": 448, "player_3_last_10_winrate": 0.5, "player_3_hotstreak": 0, "player_4_champion": 25, "player_4_points": 1818, "player_4_winrate": 0.5670103092783505, "player_4_summoner_level": 343, "player_4_last_10_winrate": 0.3, "player_4_hotstreak": 0, "player_5_champion": 516, "player_5_points": 1613, "player_5_winrate": 0.5244755244755245, "player_5_summoner_level": 508, "player_5_last_10_winrate": 0.3, "player_5_hotstreak": 0, "player_6_champion": 141, "player_6_points": 1705, "player_6_winrate": 0.5043478260869565, "player_6_summoner_level": 47, "player_6_last_10_winrate": 0.5, "player_6_hotstreak": 0, "player_7_champion": 90, "player_7_points": 1500, "player_7_winrate": 0.5537190082644629, "player_7_summoner_level": 157, "player_7_last_10_winrate": 0.4, "player_7_hotstreak": 0, "player_8_champion": 523, "player_8_points": 1649, "player_8_winrate": 0.5769230769230769, "player_8_summoner_level": 388, "player_8_last_10_winrate": 0.6, "player_8_hotstreak": 0, "player_9_champion": 412, "player_9_points": 1600, "player_9_winrate": 0.4939759036144578, "player_9_summoner_level": 316, "player_9_last_10_winrate": 0.3, "player_9_hotstreak": 0}